logue/__init__.py
logue/logue.py
internalmonologue-0.0.14.dist-info/LICENSE
internalmonologue-0.0.14.dist-info/METADATA
internalmonologue-0.0.14.dist-info/WHEEL
internalmonologue-0.0.14.dist-info/entry_points.txt
internalmonologue-0.0.14.dist-info/top_level.txt
internalmonologue-0.0.14.dist-info/RECORD
