Metadata-Version: 2.1
Name: internalmonologue
Version: 0.0.14
Summary: Internal Monologue will help you journal
Home-page: https://github.com/devashishmulye/internal-monologue
Author: Devashish Mulye
Author-email: devashish.mulye@gmail.com
License: UNKNOWN
Platform: UNKNOWN
Classifier: Programming Language :: Python :: 3
Classifier: License :: OSI Approved :: MIT License
Classifier: Operating System :: OS Independent
Requires-Python: >=2.7
Requires-Dist: requests (>=2.18.0)
